{
   "title": "Net profits/loss of Italian company Dolce & Gabbana in 2014 to 2018",
   "xAxis": "Year",
   "yAxis": "Net profits/loss in million euros",
   "columnType": "two",
   "graphType": "line",
   "summaryType": "baseline",
   "summary": [
      "The highest Net profits/loss in million euros, of value 24.11 was reached at Year 2018",
      "Minimum Net profits/loss in million euros about 24.11 was reached at Year 2018"
   ],
   "min_summary": [],
   "mid_summary": [
      "The highest Net profits/loss in million euros, of value 24.11 was reached at Year 2018",
      "Minimum Net profits/loss in million euros about 24.11 was reached at Year 2018"
   ],
   "max_summary": [
      "The highest Net profits/loss in million euros, of value 24.11 was reached at Year 2018",
      "Minimum Net profits/loss in million euros about 24.11 was reached at Year 2018"
   ],
   "trends": [],
   "data": [
      {
         "Year": "2018",
         "Net profits/loss in million euros": 24.11
      },
      {
         "Year": "2017",
         "Net profits/loss in million euros": 27.55
      },
      {
         "Year": "2016",
         "Net profits/loss in million euros": 3.73
      },
      {
         "Year": "2015",
         "Net profits/loss in million euros": 20.89
      },
      {
         "Year": "2014",
         "Net profits/loss in million euros": 13.71
      }
   ]
}