{
   "title": "Leading Croatian national team players at FIFA World Cup 2018 , by market value",
   "xAxis": "Month",
   "yAxis": "Market value in million euros",
   "columnType": "two",
   "graphType": "bar",
   "summaryType": "baseline",
   "summary": [
      "This is a bar chart representing Month in the x axis and Market value in million euros in the y axis. ",
      "The Market value in million euros is appeared to be the highest at Month Ivan Rakitic and lowest at Month Dominik Livakovic. ",
      "The Market value in million euros of Month Dominik Livakovic is 33.33% smaller than the maximum value at Ivan Rakitic. "
   ],
   "min_summary": [
      "This is a bar chart representing Month in the x axis and Market value in million euros in the y axis. ",
      "The Market value in million euros is appeared to be the highest at Month Ivan Rakitic and lowest at Month Dominik Livakovic. "
   ],
   "mid_summary": [
      "This is a bar chart representing Month in the x axis and Market value in million euros in the y axis. ",
      "The Market value in million euros is appeared to be the highest at Month Ivan Rakitic and lowest at Month Dominik Livakovic. ",
      "The Market value in million euros of Month Dominik Livakovic is 33.33% smaller than the maximum value at Ivan Rakitic. "
   ],
   "max_summary": [
      "This bar chart has 23 columns on the x axis representing Month, and Market value in million euros in each Month on the y axis. ",
      "Month Ivan Rakitic has the highest Market value in million euros and Dominik Livakovic has the lowest Market value in million euros. ",
      "There is a difference of 48.5 between the maximum Month Ivan Rakitic and minimum Month Dominik Livakovic. ",
      "Month Ivan Rakitic is higher than any other Months with value 50.0, followed by Ivan Perisic, and Mateo Kovacic. Down to Month Dominik Livakovic with the lowest value 1.5. ",
      "Overall Market value in million euros has reduced over the Months. ",
      "Similar Market value in million euros is found in Month Andrej Kramaric, and Marcelo Brozovic. ",
      "The highest value 50.0 at Ivan Rakitic is almost 3.16 times larger than the average value 15.83. "
   ],
   "trends": [
      {},
      {
         "7": 0,
         "12": 0
      },
      {
         "7": 22,
         "12": 22
      },
      {}
   ],
   "data": [
      {
         "Month": "Ivan Rakitic",
         "Market value in million euros": 50.0
      },
      {
         "Month": "Ivan Perisic",
         "Market value in million euros": 40.0
      },
      {
         "Month": "Mateo Kovacic",
         "Market value in million euros": 30.0
      },
      {
         "Month": "Andrej Kramaric",
         "Market value in million euros": 27.0
      },
      {
         "Month": "Marcelo Brozovic",
         "Market value in million euros": 27.0
      },
      {
         "Month": "Luka Modric",
         "Market value in million euros": 25.0
      },
      {
         "Month": "Sime Vrsaljko",
         "Market value in million euros": 25.0
      },
      {
         "Month": "Dejan Lovren",
         "Market value in million euros": 20.0
      },
      {
         "Month": "Mario Mandzukic",
         "Market value in million euros": 18.0
      },
      {
         "Month": "Milan Badelj",
         "Market value in million euros": 15.0
      },
      {
         "Month": "Marko Pjaca",
         "Market value in million euros": 15.0
      },
      {
         "Month": "Nikola Kalinic",
         "Market value in million euros": 14.0
      },
      {
         "Month": "Ante Rebic",
         "Market value in million euros": 10.0
      },
      {
         "Month": "Duje Caleta\u2013Car",
         "Market value in million euros": 10.0
      },
      {
         "Month": "Domagoj Vida",
         "Market value in million euros": 7.0
      },
      {
         "Month": "Lovre Kalinic",
         "Market value in million euros": 6.5
      },
      {
         "Month": "Tin Jedvaj",
         "Market value in million euros": 5.0
      },
      {
         "Month": "Danijel Subasic",
         "Market value in million euros": 4.5
      },
      {
         "Month": "Vedran Corluka",
         "Market value in million euros": 4.0
      },
      {
         "Month": "Ivan Strinic",
         "Market value in million euros": 4.0
      },
      {
         "Month": "Filip Bradaric",
         "Market value in million euros": 3.5
      },
      {
         "Month": "Josip Pivaric",
         "Market value in million euros": 2.0
      },
      {
         "Month": "Dominik Livakovic",
         "Market value in million euros": 1.5
      }
   ]
}