{
   "title": "Test",
   "xAxis": "Year",
   "yAxis": "Number of deaths",
   "columnType": "two",
   "graphType": "line",
   "summaryType": "baseline",
   "summary": [
      "This line chart has an x axis representing Year and a y axis representing Number of deaths, with a total of 26 data points.",
      " Overall Number of deaths has increased over the Year",
      "Number of deaths is gradually decreasing from 1993 to 1994, rapidly increasing from 1994 to 1995, gradually constant from 1995 to 1998, gradually increasing from 1998 to 1999, gradually decreasing from 1999 to 2001, rapidly increasing from 2001 to 2002, gradually decreasing from 2002 to 2003, gradually increasing from 2003 to 2004, gradually constant from 2004 to 2013, gradually increasing from 2013 to 2014, and lastly roughly constant from 2014 to 2018.",
      "The steepest increase occurs in between the Year 2013 and 2014.",
      "Max Number of deaths about 100.0 was recorded at Year 2018",
      "Min Number of deaths about 19.0 was recorded at Year 1994",
      "#########################################################################",
      "This line chart has an x axis representing Year and a y axis representing Number of deaths, with a total of 26 data points. The chart has 7 significant trends.",
      " The longest trend is extremely increasing which exists from 2011 to 2018.",
      " Likewise, the next significant trend is slightly decreasing which exists from 2008 to 2011.",
      " Conversely, the next significant trend is moderately decreasing which exists from 2005 to 2008.",
      " Conversely, the next significant trend is moderately decreasing which exists from 2002 to 2005.",
      " On the contrary, the next significant trend is slightly decreasing which exists from 1999 to 2002.",
      " On the contrary, the next significant trend is extremely increasing which exists from 1996 to 1999.",
      " Similarly, the next significant trend is moderately increasing which exists from 1993 to 1996."
   ],
   "trends": [
      {},
      {
         "1": "0",
         "12": "7"
      },
      {
         "3": "7",
         "14": "10"
      },
      {
         "3": "10",
         "14": "13"
      },
      {
         "3": "13",
         "14": "16"
      },
      {
         "3": "16",
         "14": "19"
      },
      {
         "3": "19",
         "14": "22"
      },
      {
         "3": "22",
         "14": "25"
      }
   ],
   "data": [
      {
         "Year": "2018",
         "Number of deaths": 100.0
      },
      {
         "Year": "2017",
         "Number of deaths": 91.0
      },
      {
         "Year": "2016",
         "Number of deaths": 96.0
      },
      {
         "Year": "2015",
         "Number of deaths": 90.0
      },
      {
         "Year": "2014",
         "Number of deaths": 85.0
      },
      {
         "Year": "2013",
         "Number of deaths": 56.0
      },
      {
         "Year": "2012",
         "Number of deaths": 49.0
      },
      {
         "Year": "2011",
         "Number of deaths": 46.0
      },
      {
         "Year": "2010",
         "Number of deaths": 48.0
      },
      {
         "Year": "2009",
         "Number of deaths": 50.0
      },
      {
         "Year": "2008",
         "Number of deaths": 59.0
      },
      {
         "Year": "2007",
         "Number of deaths": 50.0
      },
      {
         "Year": "2006",
         "Number of deaths": 49.0
      },
      {
         "Year": "2005",
         "Number of deaths": 50.0
      },
      {
         "Year": "2004",
         "Number of deaths": 43.0
      },
      {
         "Year": "2003",
         "Number of deaths": 33.0
      },
      {
         "Year": "2002",
         "Number of deaths": 51.0
      },
      {
         "Year": "2001",
         "Number of deaths": 28.0
      },
      {
         "Year": "2000",
         "Number of deaths": 40.0
      },
      {
         "Year": "1999",
         "Number of deaths": 67.0
      },
      {
         "Year": "1998",
         "Number of deaths": 48.0
      },
      {
         "Year": "1997",
         "Number of deaths": 41.0
      },
      {
         "Year": "1996",
         "Number of deaths": 33.0
      },
      {
         "Year": "1995",
         "Number of deaths": 35.0
      },
      {
         "Year": "1994",
         "Number of deaths": 19.0
      },
      {
         "Year": "1993",
         "Number of deaths": 37.0
      }
   ]
}