{
   "title": "Test",
   "xAxis": "Soccer Club",
   "yAxis": "Number of titles",
   "columnType": "two",
   "graphType": "bar",
   "summaryType": "baseline",
   "summary": [
      "This bar chart has 28 categories on the x axis representing Soccer Club, and Number of titles in each Soccer Club on the y axis.",
      " The highest category is found at Sevilla FC where Number of titles is 5.0.",
      " Followed by 5.0 in .",
      " The lowest category is found at Ipswich Town FC where Number of titles is 1.0.",
      " The highest value at Sevilla FC is almost 5.0 times larger than the minimum value of Ipswich Town FC. ",
      " The highest value at Sevilla FC is almost 5.0 times larger than the minimum value of Ipswich Town FC. ",
      " The difference between the max Soccer Club Sevilla FC and min Soccer Club Ipswich Town FC is 4.0. "
   ],
   "trends": [
      {},
      {
         "7": 0,
         "12": 0
      },
      {
         "7": 13,
         "12": 13
      },
      {}
   ],
   "data": [
      {
         "Soccer Club": "Sevilla FC",
         "Number of titles": 5.0
      },
      {
         "Soccer Club": "Atletico Madrid",
         "Number of titles": 3.0
      },
      {
         "Soccer Club": "FC Internazionale Milano",
         "Number of titles": 3.0
      },
      {
         "Soccer Club": "Liverpool FC",
         "Number of titles": 3.0
      },
      {
         "Soccer Club": "Juventus",
         "Number of titles": 3.0
      },
      {
         "Soccer Club": "VfL Borussia M\u00f6nchengladbach",
         "Number of titles": 2.0
      },
      {
         "Soccer Club": "Chelsea FC",
         "Number of titles": 2.0
      },
      {
         "Soccer Club": "IFK G\u00f6teborg",
         "Number of titles": 2.0
      },
      {
         "Soccer Club": "Feyenoord",
         "Number of titles": 2.0
      },
      {
         "Soccer Club": "Parma FC",
         "Number of titles": 2.0
      },
      {
         "Soccer Club": "Real Madrid CF",
         "Number of titles": 2.0
      },
      {
         "Soccer Club": "Tottenham Hotspur FC",
         "Number of titles": 2.0
      },
      {
         "Soccer Club": "FC Porto",
         "Number of titles": 2.0
      },
      {
         "Soccer Club": "Ipswich Town FC",
         "Number of titles": 1.0
      },
      {
         "Soccer Club": "FC Zenit",
         "Number of titles": 1.0
      },
      {
         "Soccer Club": "PSV Eindhoven",
         "Number of titles": 1.0
      },
      {
         "Soccer Club": "FC Bayern Munich",
         "Number of titles": 1.0
      },
      {
         "Soccer Club": "SSC Napoli",
         "Number of titles": 1.0
      },
      {
         "Soccer Club": "RSC Anderlecht",
         "Number of titles": 1.0
      },
      {
         "Soccer Club": "CSKA Moscow",
         "Number of titles": 1.0
      },
      {
         "Soccer Club": "Valencia CF",
         "Number of titles": 1.0
      },
      {
         "Soccer Club": "FC Schalke 04",
         "Number of titles": 1.0
      },
      {
         "Soccer Club": "Bayer 04 Leverkusen",
         "Number of titles": 1.0
      },
      {
         "Soccer Club": "Manchester United",
         "Number of titles": 1.0
      },
      {
         "Soccer Club": "AFC Ajax",
         "Number of titles": 1.0
      },
      {
         "Soccer Club": "FC Shakhtar Donetsk",
         "Number of titles": 1.0
      },
      {
         "Soccer Club": "Galatasaray AS",
         "Number of titles": 1.0
      },
      {
         "Soccer Club": "Eintracht Frankfurt",
         "Number of titles": 1.0
      }
   ]
}