{
   "title": "Ratio of government expenditure to gross domestic product ( GDP ) in Malaysia 2024",
   "xAxis": "Year",
   "yAxis": "Ratio of government expenditure to GDP",
   "columnType": "two",
   "graphType": "line",
   "summaryType": "baseline",
   "summary": [
      " Overall Ratio of government expenditure to GDP has decreased over the Year.",
      "Ratio of government expenditure to GDP is gradually decreasing from 2014 to 2017, slightly increasing from 2017 to 2018, roughly constant from 2018 to 2019, slightly decreasing from 2019 to 2020, and lastly roughly constant from 2020 to 2023.",
      "The steepest decrease occurs in between the Year 2019 and 2020.",
      "Maximum Ratio of government expenditure to GDP, about 25.96 was reported at Year 2014",
      "Minimum Ratio of government expenditure to GDP about 20.37 was reached at Year 2023"
   ],
   "min_summary": [
      " Overall Ratio of government expenditure to GDP has decreased over the Year.",
      "Ratio of government expenditure to GDP is gradually decreasing from 2014 to 2017, slightly increasing from 2017 to 2018, roughly constant from 2018 to 2019, slightly decreasing from 2019 to 2020, and lastly roughly constant from 2020 to 2023."
   ],
   "mid_summary": [
      " In general Ratio of government expenditure to GDP has fallen over the Year.",
      "Ratio of government expenditure to GDP is gradually decreasing from 2014 to 2017, slightly increasing from 2017 to 2018, roughly constant from 2018 to 2019, slightly decreasing from 2019 to 2020, and lastly roughly constant from 2020 to 2023.",
      "The most drastic decrease took place within the Year 2019 and 2020.",
      "Maximum Ratio of government expenditure to GDP, about 25.96 was reported at Year 2014",
      "Minimum Ratio of government expenditure to GDP about 20.37 was reached at Year 2023"
   ],
   "max_summary": [
      " In general Ratio of government expenditure to GDP has fallen over the Year.",
      "Ratio of government expenditure to GDP is gradually decreasing from 2014 to 2017, slightly increasing from 2017 to 2018, roughly constant from 2018 to 2019, slightly decreasing from 2019 to 2020, and lastly roughly constant from 2020 to 2023.",
      "The most drastic decrease took place within the Year 2019 and 2020.",
      "Maximum Ratio of government expenditure to GDP, about 25.96 was reported at Year 2014",
      "Minimum Ratio of government expenditure to GDP about 20.37 was reached at Year 2023"
   ],
   "trends": [],
   "data": [
      {
         "Year": "2024",
         "Ratio of government expenditure to GDP": 20.35
      },
      {
         "Year": "2023",
         "Ratio of government expenditure to GDP": 20.37
      },
      {
         "Year": "2022",
         "Ratio of government expenditure to GDP": 20.46
      },
      {
         "Year": "2021",
         "Ratio of government expenditure to GDP": 20.41
      },
      {
         "Year": "2020",
         "Ratio of government expenditure to GDP": 20.54
      },
      {
         "Year": "2019",
         "Ratio of government expenditure to GDP": 22.97
      },
      {
         "Year": "2018",
         "Ratio of government expenditure to GDP": 22.7
      },
      {
         "Year": "2017",
         "Ratio of government expenditure to GDP": 21.58
      },
      {
         "Year": "2016",
         "Ratio of government expenditure to GDP": 22.7
      },
      {
         "Year": "2015",
         "Ratio of government expenditure to GDP": 24.71
      },
      {
         "Year": "2014",
         "Ratio of government expenditure to GDP": 25.96
      }
   ]
}