{
   "title": "Average attendance in the National Football League 2019",
   "xAxis": "Year",
   "yAxis": "Average attendance",
   "columnType": "two",
   "graphType": "line",
   "summaryType": "baseline",
   "summary": [
      " Overall Average attendance has decreased over the Year.",
      "Average attendance is roughly increasing from 2009 to 2010, roughly constant from 2010 to 2015, slightly increasing from 2015 to 2016, and lastly slightly decreasing from 2016 to 2017.",
      "The most drastic decrease took place within the Year 2016 and 2017.",
      "The highest Average attendance, of value 69487.0 was reached at Year 2016",
      "Minimum Average attendance about 66957.0 was reached at Year 2010"
   ],
   "min_summary": [
      " In general Average attendance has stayed the same over the Year.",
      "Average attendance is roughly increasing from 2009 to 2010, roughly constant from 2010 to 2015, slightly increasing from 2015 to 2016, and lastly slightly decreasing from 2016 to 2017."
   ],
   "mid_summary": [
      " In general Average attendance has stayed the same over the Year.",
      "Average attendance is roughly increasing from 2009 to 2010, roughly constant from 2010 to 2015, slightly increasing from 2015 to 2016, and lastly slightly decreasing from 2016 to 2017.",
      "The steepest decrease occurs in between the Year 2016 and 2017.",
      "The highest Average attendance, of value 69487.0 was reached at Year 2016",
      "Minimum Average attendance about 66957.0 was reached at Year 2010"
   ],
   "max_summary": [
      " In general Average attendance has stayed the same over the Year.",
      "Average attendance is roughly increasing from 2009 to 2010, roughly constant from 2010 to 2015, slightly increasing from 2015 to 2016, and lastly slightly decreasing from 2016 to 2017.",
      "The steepest decrease occurs in between the Year 2016 and 2017.",
      "The highest Average attendance, of value 69487.0 was reached at Year 2016",
      "Minimum Average attendance about 66957.0 was reached at Year 2010"
   ],
   "trends": [],
   "data": [
      {
         "Year": "2019",
         "Average attendance": 66151.0
      },
      {
         "Year": "2018",
         "Average attendance": 67040.0
      },
      {
         "Year": "2017",
         "Average attendance": 67405.0
      },
      {
         "Year": "2016",
         "Average attendance": 69487.0
      },
      {
         "Year": "2015",
         "Average attendance": 68216.0
      },
      {
         "Year": "2014",
         "Average attendance": 68331.0
      },
      {
         "Year": "2013",
         "Average attendance": 68397.0
      },
      {
         "Year": "2012",
         "Average attendance": 67632.0
      },
      {
         "Year": "2011",
         "Average attendance": 67419.0
      },
      {
         "Year": "2010",
         "Average attendance": 66957.0
      },
      {
         "Year": "2009",
         "Average attendance": 67506.0
      },
      {
         "Year": "2008",
         "Average attendance": 68245.0
      }
   ]
}