{
   "title": "Test",
   "xAxis": "Year",
   "yAxis": "Spending in billion euros",
   "columnType": "two",
   "graphType": "line",
   "summaryType": "baseline",
   "summary": [
      "This line chart has an x axis representing Year and a y axis representing Spending in billion euros, with a total of 8 data points.",
      " Overall Spending in billion euros has increased over the Year",
      "Spending in billion euros is gradually constant from 2012 to 2018, and lastly gradually increasing from 2018 to 2028.",
      "The steepest increase occurs in between the Year 2018 and 2028.",
      "Max Spending in billion euros about 26.4 was recorded at Year 2028",
      "Min Spending in billion euros about 12.2 was recorded at Year 2012",
      "#########################################################################",
      "This line chart has an x axis representing Year and a y axis representing Spending in billion euros with a total of 8 data points. The chart has one significant trend.",
      " This trend is increasing which exists from 2028 to 2012."
   ],
   "trends": [
      {},
      {
         "3": "0",
         "14": "7"
      }
   ],
   "data": [
      {
         "Year": "2028",
         "Spending in billion euros": 26.4
      },
      {
         "Year": "2018",
         "Spending in billion euros": 19.4
      },
      {
         "Year": "2017",
         "Spending in billion euros": 18.1
      },
      {
         "Year": "2016",
         "Spending in billion euros": 15.6
      },
      {
         "Year": "2015",
         "Spending in billion euros": 14.5
      },
      {
         "Year": "2014",
         "Spending in billion euros": 13.9
      },
      {
         "Year": "2013",
         "Spending in billion euros": 12.8
      },
      {
         "Year": "2012",
         "Spending in billion euros": 12.2
      }
   ]
}