{
   "title": "Unemployment rate in Canada 2024",
   "xAxis": "Year",
   "yAxis": "Unemployment rate",
   "columnType": "two",
   "graphType": "line",
   "summaryType": "baseline",
   "summary": [
      " In general Unemployment rate has fallen over the Year.",
      "Unemployment rate is roughly constant from 2015 to 2016, and finally slightly decreasing from 2016 to 2018.",
      "The steepest decrease occurs in between the Year 2016 and 2017.",
      "Maximum Unemployment rate, about 6.99 was reported at Year 2016",
      "The lowest Unemployment rate, of value 5.83 was reported at Year 2018"
   ],
   "min_summary": [
      " In general Unemployment rate has fallen over the Year.",
      "Unemployment rate is roughly constant from 2015 to 2016, and finally slightly decreasing from 2016 to 2018."
   ],
   "mid_summary": [
      " Overall Unemployment rate has decreased over the Year.",
      "Unemployment rate is roughly constant from 2015 to 2016, and finally slightly decreasing from 2016 to 2018.",
      "The steepest decrease occurs in between the Year 2016 and 2017.",
      "Maximum Unemployment rate, about 6.99 was reported at Year 2016",
      "The lowest Unemployment rate, of value 5.83 was reported at Year 2018"
   ],
   "max_summary": [
      " Overall Unemployment rate has decreased over the Year.",
      "Unemployment rate is roughly constant from 2015 to 2016, and finally slightly decreasing from 2016 to 2018.",
      "The steepest decrease occurs in between the Year 2016 and 2017.",
      "Maximum Unemployment rate, about 6.99 was reported at Year 2016",
      "The lowest Unemployment rate, of value 5.83 was reported at Year 2018"
   ],
   "trends": [],
   "data": [
      {
         "Year": "2024",
         "Unemployment rate": 6.5
      },
      {
         "Year": "2023",
         "Unemployment rate": 6.39
      },
      {
         "Year": "2022",
         "Unemployment rate": 6.25
      },
      {
         "Year": "2021",
         "Unemployment rate": 6.12
      },
      {
         "Year": "2020",
         "Unemployment rate": 6.0
      },
      {
         "Year": "2019",
         "Unemployment rate": 5.79
      },
      {
         "Year": "2018",
         "Unemployment rate": 5.83
      },
      {
         "Year": "2017",
         "Unemployment rate": 6.33
      },
      {
         "Year": "2016",
         "Unemployment rate": 6.99
      },
      {
         "Year": "2015",
         "Unemployment rate": 6.9
      },
      {
         "Year": "2014",
         "Unemployment rate": 6.93
      }
   ]
}