{
   "title": "Global leading fishing nations 2017",
   "xAxis": "Country",
   "yAxis": "Capture in million metric tons",
   "columnType": "two",
   "graphType": "bar",
   "summaryType": "baseline",
   "summary": [
      "This bar chart has 10 columns on the x axis representing Country, and Capture in million metric tons in each Country on the y axis. ",
      "The Capture in million metric tons is highest at Country China and lowest at Country Myanmar. ",
      "The minimum Country Myanmar has got 7.15 times less Capture in million metric tons than the maximum Country China. "
   ],
   "min_summary": [
      "This is a bar chart representing Country in the x axis and Capture in million metric tons in the y axis. ",
      "The maximum Capture in million metric tons 15.37 is found at Country China and the minimum is found at Myanmar where Country is 2.15. "
   ],
   "mid_summary": [
      "This bar chart has 10 columns on the x axis representing Country, and Capture in million metric tons in each Country on the y axis. ",
      "The Capture in million metric tons is highest at Country China and lowest at Country Myanmar. ",
      "The minimum Country Myanmar has got 7.15 times less Capture in million metric tons than the maximum Country China. "
   ],
   "max_summary": [
      "This is a bar chart. It shows Capture in million metric tons for 10 number of Countrys. ",
      "Country China has the highest Capture in million metric tons and Myanmar has the lowest Capture in million metric tons. ",
      "The highest value at Country China is 7.15x times more than the lowest value at Myanmar. ",
      "Country China is higher than any other Countrys with value 15.37, followed by Indonesia, and India. Down to Country Myanmar with the lowest value 2.15. ",
      "The Country Myanmar tends to be 2.92 percent lower than average. "
   ],
   "trends": [
      {},
      {
         "7": 0,
         "12": 0
      },
      {
         "7": 9,
         "12": 9
      },
      {}
   ],
   "data": [
      {
         "Country": "China",
         "Capture in million metric tons": 15.37
      },
      {
         "Country": "Indonesia",
         "Capture in million metric tons": 6.69
      },
      {
         "Country": "India",
         "Capture in million metric tons": 5.43
      },
      {
         "Country": "United States",
         "Capture in million metric tons": 5.04
      },
      {
         "Country": "Russia",
         "Capture in million metric tons": 4.87
      },
      {
         "Country": "Peru",
         "Capture in million metric tons": 4.16
      },
      {
         "Country": "Vietnam",
         "Capture in million metric tons": 3.28
      },
      {
         "Country": "Japan",
         "Capture in million metric tons": 3.2
      },
      {
         "Country": "Norway",
         "Capture in million metric tons": 2.37
      },
      {
         "Country": "Myanmar",
         "Capture in million metric tons": 2.15
      }
   ]
}