{
   "title": "Population growth in Mexico 2018",
   "xAxis": "Year",
   "yAxis": "Population growth compared to the previous year",
   "columnType": "two",
   "graphType": "line",
   "summaryType": "baseline",
   "summary": [
      " Overall Population growth compared to the previous year has decreased over the Year.",
      "Population growth compared to the previous year is roughly constant from 2008 to 2009, and finally slightly decreasing from 2009 to 2017.",
      "The steepest decrease occurs in between the Year 2010 and 2011.",
      "Maximum Population growth compared to the previous year, about 1.5 was reported at Year 2008",
      "Minimum Population growth compared to the previous year about 1.16 was reached at Year 2017"
   ],
   "min_summary": [
      " In general Population growth compared to the previous year has fallen over the Year.",
      "Population growth compared to the previous year is roughly constant from 2008 to 2009, and finally slightly decreasing from 2009 to 2017."
   ],
   "mid_summary": [
      " Overall Population growth compared to the previous year has decreased over the Year.",
      "Population growth compared to the previous year is roughly constant from 2008 to 2009, and finally slightly decreasing from 2009 to 2017.",
      "The most drastic decrease took place within the Year 2010 and 2011.",
      "Maximum Population growth compared to the previous year, about 1.5 was reported at Year 2008",
      "Minimum Population growth compared to the previous year about 1.16 was reached at Year 2017"
   ],
   "max_summary": [
      " In general Population growth compared to the previous year has fallen over the Year.",
      "Population growth compared to the previous year is roughly constant from 2008 to 2009, and finally slightly decreasing from 2009 to 2017.",
      "The steepest decrease occurs in between the Year 2010 and 2011.",
      "Maximum Population growth compared to the previous year, about 1.5 was reported at Year 2008",
      "Minimum Population growth compared to the previous year about 1.16 was reached at Year 2017"
   ],
   "trends": [],
   "data": [
      {
         "Year": "2018",
         "Population growth compared to the previous year": 1.13
      },
      {
         "Year": "2017",
         "Population growth compared to the previous year": 1.16
      },
      {
         "Year": "2016",
         "Population growth compared to the previous year": 1.2
      },
      {
         "Year": "2015",
         "Population growth compared to the previous year": 1.24
      },
      {
         "Year": "2014",
         "Population growth compared to the previous year": 1.28
      },
      {
         "Year": "2013",
         "Population growth compared to the previous year": 1.32
      },
      {
         "Year": "2012",
         "Population growth compared to the previous year": 1.36
      },
      {
         "Year": "2011",
         "Population growth compared to the previous year": 1.39
      },
      {
         "Year": "2010",
         "Population growth compared to the previous year": 1.44
      },
      {
         "Year": "2009",
         "Population growth compared to the previous year": 1.48
      },
      {
         "Year": "2008",
         "Population growth compared to the previous year": 1.5
      }
   ]
}